<?xml version="1.0" encoding="UTF-8"?>
<MetaDataObject xmlns="http://v8.1c.ru/8.3/MDClasses" xmlns:app="http://v8.1c.ru/8.2/managed-application/core" xmlns:cfg="http://v8.1c.ru/8.1/data/enterprise/current-config" xmlns:cmi="http://v8.1c.ru/8.2/managed-application/cmi" xmlns:ent="http://v8.1c.ru/8.1/data/enterprise" xmlns:lf="http://v8.1c.ru/8.2/managed-application/logform" xmlns:style="http://v8.1c.ru/8.1/data/ui/style" xmlns:sys="http://v8.1c.ru/8.1/data/ui/fonts/system" xmlns:v8="http://v8.1c.ru/8.1/data/core" xmlns:v8ui="http://v8.1c.ru/8.1/data/ui" xmlns:web="http://v8.1c.ru/8.1/data/ui/colors/web" xmlns:win="http://v8.1c.ru/8.1/data/ui/colors/windows" xmlns:xen="http://v8.1c.ru/8.3/xcf/enums" xmlns:xpr="http://v8.1c.ru/8.3/xcf/predef" xmlns:xr="http://v8.1c.ru/8.3/xcf/readable" xmlns:xs="http://www.w3.org/2001/XMLSchema" xmlns:xsi="http://www.w3.org/2001/XMLSchema-instance" version="2.1">
	<Constant uuid="1f02e6a5-fea5-4559-a9d7-9390c1f29c70">
		<InternalInfo>
			<xr:GeneratedType name="ConstantManager.bitmobile_НеЗаписыватьСобытияСинхронизацииВЖурнал" category="Manager">
				<xr:TypeId>627062c6-07b4-4072-bdcd-3d2a2ff1f3fe</xr:TypeId>
				<xr:ValueId>c5bdde89-4470-4caf-973d-b950cf973c30</xr:ValueId>
			</xr:GeneratedType>
			<xr:GeneratedType name="ConstantValueManager.bitmobile_НеЗаписыватьСобытияСинхронизацииВЖурнал" category="ValueManager">
				<xr:TypeId>a65d3676-22a6-450a-ac3c-18a7fb377047</xr:TypeId>
				<xr:ValueId>2a4b932c-4527-4a6c-bd13-654fc0c1e714</xr:ValueId>
			</xr:GeneratedType>
		</InternalInfo>
		<Properties>
			<Name>bitmobile_НеЗаписыватьСобытияСинхронизацииВЖурнал</Name>
			<Synonym>
				<v8:item>
					<v8:lang>en</v8:lang>
					<v8:content>Do not write synchronization event log (bitmobile)</v8:content>
				</v8:item>
				<v8:item>
					<v8:lang>ru</v8:lang>
					<v8:content>Не записывать события синхронизации в журнал (bitmobile)</v8:content>
				</v8:item>
				<v8:item>
					<v8:lang>cz</v8:lang>
					<v8:content>Do not write synchronization event log (bitmobile)</v8:content>
				</v8:item>
			</Synonym>
			<Comment/>
			<Type>
				<v8:Type>xs:boolean</v8:Type>
			</Type>
			<UseStandardCommands>true</UseStandardCommands>
			<DefaultForm/>
			<ExtendedPresentation/>
			<Explanation/>
			<PasswordMode>false</PasswordMode>
			<Format/>
			<EditFormat/>
			<ToolTip/>
			<MarkNegatives>false</MarkNegatives>
			<Mask/>
			<MultiLine>false</MultiLine>
			<ExtendedEdit>false</ExtendedEdit>
			<MinValue xsi:nil="true"/>
			<MaxValue xsi:nil="true"/>
			<FillChecking>DontCheck</FillChecking>
			<ChoiceFoldersAndItems>Items</ChoiceFoldersAndItems>
			<ChoiceParameterLinks/>
			<ChoiceParameters/>
			<QuickChoice>Auto</QuickChoice>
			<ChoiceForm/>
			<LinkByType/>
			<ChoiceHistoryOnInput>Auto</ChoiceHistoryOnInput>
			<DataLockControlMode>Automatic</DataLockControlMode>
		</Properties>
	</Constant>
</MetaDataObject>